LICENSE
MANIFEST.in
README.md
setup.py
pyhipku/__init__.py
pyhipku/decode.py
pyhipku/dictionary.py
pyhipku/encode.py
pyhipku.egg-info/PKG-INFO
pyhipku.egg-info/SOURCES.txt
pyhipku.egg-info/dependency_links.txt
pyhipku.egg-info/top_level.txt
pyhipku/test/test_hipku.py