Metadata-Version: 1.1
Name: pyhipku
Version: 0.1.0
Summary: Encode any IP address as a haiku
Home-page: http://github.com/lord63/pyhipku/
Author: lord63
Author-email: lord63.j@gmail.com
License: MIT
Keywords: ip haiku
Platform: UNKNOWN
Classifier: Development Status :: 4 - Beta
Classifier: Operating System :: POSIX
Classifier: Operating System :: POSIX :: Linux
Classifier: License :: OSI Approved :: MIT License
Classifier: Programming Language :: Python :: 2
Classifier: Programming Language :: Python :: 2.7
Classifier: Programming Language :: Python
Classifier: Topic :: Software Development :: Libraries :: Python Modules
